dictionary/__init__.py
dictionary/dictionary.py
gunes_ustunalp_dictionary-2.0.0.dist-info/METADATA
gunes_ustunalp_dictionary-2.0.0.dist-info/WHEEL
gunes_ustunalp_dictionary-2.0.0.dist-info/top_level.txt
gunes_ustunalp_dictionary-2.0.0.dist-info/RECORD
