Metadata-Version: 2.1
Name: gunes-ustunalp-dictionary
Version: 2.0.0
Summary: UNKNOWN
Author: Asım Güneş Üstünalp
License: UNKNOWN
Platform: UNKNOWN
Requires-Python: >=3.8
Requires-Dist: requests (>=2.23.0)
